client.py
fivem_israel-1.0.1.dist-info/licenses/LICENSE
fivem_israel-1.0.1.dist-info/METADATA
fivem_israel-1.0.1.dist-info/WHEEL
fivem_israel-1.0.1.dist-info/top_level.txt
fivem_israel-1.0.1.dist-info/RECORD
