Metadata-Version: 2.4
Name: fivem_israel
Version: 1.0.1
Summary: Easy vote handling for FiveM Israel in Python
Author: Ticker
License: MIT
Requires-Python: >=3.8
License-File: LICENSE
Requires-Dist: websockets>=10.0
Dynamic: license-file
